design1/__init__.py
design1/dashboard.py
design1/pix_source_rc.py
design1/ui_Dashboard.py
pyqt5_gui_yyj-0.1.12.dist-info/LICENSE
pyqt5_gui_yyj-0.1.12.dist-info/METADATA
pyqt5_gui_yyj-0.1.12.dist-info/WHEEL
pyqt5_gui_yyj-0.1.12.dist-info/top_level.txt
pyqt5_gui_yyj-0.1.12.dist-info/RECORD
